<?xml version="1.0" encoding="windows-1251"?>

<string_table>

    <string id="mag_kriss45">
		<text>Standard .45 ACP Vector Magazine</text>
	</string>
	<string id="mag_kriss45_descr">
		<text>%c[pda_white]PROPERTIES:</text>
	</string>
	
	<string id="mag_kriss9">
		<text>Modified 9x19 Vector Magazine</text>
	</string>
	<string id="mag_kriss9_descr">
		<text>%c[pda_white]PROPERTIES:</text>
	</string>
	
	<string id="ext_mag_kriss_drum">
		<text>.45 ACP Vector Drum Magazine</text>
	</string>
	<string id="ext_mag_kriss_drum_descr">
		<text>%c[pda_white]PROPERTIES:</text>
	</string>
	
	<string id="ext_mag_kriss9_drum">
		<text>Modified 9x19 Vector Drum Magazine</text>
	</string>
	<string id="ext_mag_kriss9_drum_descr">
		<text>%c[pda_white]PROPERTIES:</text>
	</string>
	
</string_table>