<?xml version="1.0" encoding="windows-1251"?>

<string_table>

<!--
	TABS
-->
	<string id="pda_btn_quests">
		<text>Area Map</text>
	</string>
	<string id="pda_btn_taskboard">
		<text>Taskboard</text>
	</string>
	<string id="pda_btn_ranking">
		<text>Statistics</text>
	</string>
	<string id="pda_btn_relations">
		<text>Relations</text>
	</string>
	<string id="pda_btn_contacts">
		<text>Contacts</text>
	</string>
	<string id="st_ui_pda_legend_scout">
		<text>Guide</text>
	</string>
	<string id="pda_btn_radio">
		<text>Radio</text>
	</string>
	<string id="pda_btn_logs">
		<text>Messages</text>
	</string>

<!--
	AREA MAP
-->

	<string id="pda_btn_quests_hint">
		<text>Show Zone Map/Task List</text>
	</string>
	<string id="missions_list">
		<text>Task List</text>
	</string>
	<string id="filter_treasures_text">
		<text>Stashes</text>
	</string>
	<string id="filter_primary_objects_text">
		<text>Areas</text>
	</string>
	<string id="filter_secondary_tasks_text">
		<text>Secondary Tasks</text>
	</string>
	<string id="filter_quest_npcs_text">
		<text>Important Objects</text>
	</string>
	<string id="ui_map_btn_up">
		<text>Move Up</text>
	</string>
	<string id="ui_map_btn_down">
		<text>Move Down</text>
	</string>
	<string id="ui_map_btn_left">
		<text>Move Left</text>
	</string>
	<string id="ui_map_btn_right">
		<text>Move Right</text>
	</string>
	<string id="ui_map_btn_zoom_in">
		<text>Zoom In</text>
	</string>
	<string id="ui_map_btn_zoom_out">
		<text>Zoom Out</text>
	</string>
	<string id="ui_map_btn_zmreset">
		<text>Zoom Reset</text>
	</string>
	<string id="ui_map_btn_legend">
		<text>Show Legend</text>
	</string>
	<string id="ui_map_btn_center">
		<text>Center On Player</text>
	</string>
	<string id="ui_task_btn_focus_center">
		<text>Center On Objective</text>
	</string>
	<string id="ui_task_btn_focus_center2">
		<text>Center On Objective</text>
	</string>

<!--
	STATISTICS
-->

	<string id="pda_btn_ranking_hint">
		<text>Show Personal Statistics</text>
	</string>
	<string id="pda_stat_1">
		<text>Time Elapsed:</text>
	</string>
	<string id="pda_stat_2">
		<text>Emissions Survived:</text>
	</string>
	<string id="pda_stat_8">
		<text>Psi-storms Survived:</text>
	</string>
	<string id="pda_stat_money">
		<text>Money:</text>
	</string>
	<string id="st_mutants_killed">
		<text>Mutants Killed</text>
	</string>
	<string id="pda_stat_4">
		<text>Mutants Killed:</text>
	</string>
	<string id="st_mm_pda_mutants_killed">
		<text>Mutants Killed</text>
	</string>
	<string id="st_stalkers_killed">
		<text>Stalkers Killed</text>
	</string>
	<string id="st_mm_pda_stalkers_killed">
		<text>Stalkers Killed</text>
	</string>
	<string id="pda_stat_5">
		<text>Stalkers Killed:</text>
	</string>
	<string id="st_helicopters downed">
		<text>Helicopters Downed</text>
	</string>
	<string id="st_mm_pda_helicopters downed">
		<text>Helicopters Downed</text>
	</string>
	<string id="pda_stat_10">
		<text>Helicopters Downed:</text>
	</string>
	<string id="pda_stat_9">
		<text>PDAs Delivered:</text>
	</string>
	<string id="pda_stat_3">
		<text>Tasks Completed:</text>
	</string>
	<string id="pda_stat_7">
		<text>Stashes Found:</text>
	</string>
	<string id="pda_stat_6">
		<text>Boxes Smashed:</text>
	</string>
	<string id="st_artefacts_found">
		<text>Artefacts Found</text>
	</string>
	<string id="st_mm_pda_artes_found">
		<text>Artefacts Found</text>
	</string>
	<string id="st_wounded_helped">
		<text>Wounded Helped</text>
	</string>
	<string id="st_mm_pda_wounded_helped">
		<text>Wounded Helped</text>
	</string>
	<string id="pda_stat_12">
		<text>Wounded Helped:</text>
	</string>
	<string id="pda_stat_13">
		<text>Level Changes:</text>
	</string>
	<string id="pda_stat_14">
		<text>Enemy Forfeits:</text>
	</string>
	<string id="pda_stat_15">
		<text>Field Dressings:</text>
	</string>
	<string id="pda_stat_17">
		<text>Achievements:</text>
	</string>
	<string id="pda_stat_18">
		<text>Levels Visited:</text>
	</string>
	<string id="pda_stat_16">
		<text>Unlocked Articles:</text>
	</string>

<!--
	UNUSED STATISTICS
-->

	<string id="pda_stat_11">
		<text>Artefacts Detected:</text>
	</string>
	<string id="st_mm_pda_items_sold">
		<text>Items Sold</text>
	</string>
	<string id="st_corpse_looted">
		<text>Corpse Looted</text>
	</string>
	<string id="st_mm_pda_corpse_looted">
		<text>Corpse Looted</text>
	</string>
	<string id="pda_stat_mutant_killed">
		<text>Most Powerful Mutant Killed</text>
	</string>

<!--
	RELATIONS
-->

	<string id="pda_btn_relations_hint">
		<text>Show Faction Relations</text>
	</string>
	<string id="pda_relations_header">
		<text>Faction Relations</text>
	</string>
	<string id="stalker">
		<text>Free Stalkers</text>
	</string>
	<string id="pda_companions_auto">
		<text>Refresh</text>
	</string>
	<string id="st_pda_display_values">
		<text>Display Values</text>
	</string>
	<string id="pda_table_value_on">
		<text>Display Text</text>
	</string>
	<string id="pda_companions_header">
		<text>Companions</text>
	</string>

<!--
	CONTACTS
-->

	<string id="pda_show_known_contacts">
		<text>Known Contacts</text>
	</string>

<!--
	GUIDE
-->

	<string id="ui_ranking_center_caption">
		<text>Achievements</text>
	</string>

<!--
	RADIO
-->

	<string id="pda_btn_radio_hint">
		<text>Show Radio and Music Player</text>
	</string>
	<string id="pda_btn_radio_title">
		<text>Radio</text>
	</string>
	<string id="pda_btn_plyr_title">
		<text>Music Player</text>
	</string>
	<string id="ui_st_radio_playing">
		<text>Playing</text>
	</string>
	<string id="ui_st_radio_playlist">
		<text>Playlist</text>
	</string>
	<string id="ui_st_radio_loop_off">
		<text>Loop Off</text>
	</string>
	<string id="ui_st_radio_loop_all">
		<text>Loop All</text>
	</string>
	<string id="ui_st_radio_loop_one">
		<text>Loop One</text>
	</string>
	<string id="ui_st_radio_shuffle_on">
		<text>Shuffle On</text>
	</string>
	<string id="ui_st_radio_shuffle_off">
		<text>Shuffle Off</text>
	</string>

<!--
	MESSAGES
-->

	<string id="pda_btn_logs_hint">
		<text>Show Message History</text>
	</string>
	<string id="ui_logs_center_caption">
		<text>Message History</text>
	</string>
	<string id="pda_filter_news">
		<text>Show News</text>
	</string>
	<string id="pda_filter_talk">
		<text>Show Dialogues</text>
	</string>
	<string id="pda_date_filter">
		<text>Filter By Date</text>
	</string>

<!--
	TIME
-->

	<string id="pda_cur_time">
		<text>Current Time:</text>
	</string>
	<string id="Time">
		<text>Time</text>
	</string>
	<string id="date">
		<text>Date</text>
	</string>
	<string id="month_january">
		<text>January</text>
	</string>
	<string id="month_february">
		<text>February</text>
	</string>
	<string id="month_march">
		<text>March</text>
	</string>
	<string id="month_april">
		<text>April</text>
	</string>
	<string id="month_may">
		<text>May</text>
	</string>
	<string id="month_june">
		<text>June</text>
	</string>
	<string id="month_july">
		<text>July</text>
	</string>
	<string id="month_august">
		<text>August</text>
	</string>
	<string id="month_september">
		<text>September</text>
	</string>
	<string id="month_october">
		<text>October</text>
	</string>
	<string id="month_november">
		<text>November</text>
	</string>
	<string id="month_december">
		<text>December</text>
	</string>

<!--
	OTHER
-->

	<string id="pda_btn_close">
		<text>Close PDA</text>
	</string>
	<string id="pda_legend_caption">
		<text>Symbols</text>
	</string>
	<string id="st_location">
		<text>Location:</text>
	</string>
	<string id="st_target">
		<text>Goal</text>
	</string>
	<string id="st_ui_pda_legend_additional_task">
		<text>Secondary Task</text>
	</string>
	<string id="st_ui_pda_legend_enemies">
		<text>Enemies</text>
	</string>
	<string id="st_ui_pda_legend_friends">
		<text>Friends</text>
	</string>
	<string id="st_ui_pda_legend_leader">
		<text>Faction Leader</text>
	</string>
	<string id="st_ui_pda_legend_main_task">
		<text>Main Task</text>
	</string>
	<string id="st_ui_pda_legend_neutrals">
		<text>Neutrals</text>
	</string>
	<string id="st_ui_pda_legend_secrets">
		<text>Stashes</text>
	</string>
	<string id="st_ui_pda_legend_squad">
		<text>Squad Commander</text>
	</string>
	<string id="st_ui_pda_legend_trader">
		<text>Trader</text>
	</string>
	<string id="trader">
		<text>Trader</text>
	</string>
	<string id="zoom_in_btn_hint">
		<text>Zoom +</text>
	</string>
	<string id="zoom_out_btn_hint">
		<text>Zoom -</text>
	</string>
	<string id="st_ui_pda_legend_mechanic">
		<text>Technician</text>
	</string>
	<string id="st_ui_pda_legend_medic">
		<text>Medic</text>
	</string>
	<string id="st_ui_pda_legend_barman">
		<text>Bartender</text>
	</string>
	<string id="st_ui_pda_legend_special">
		<text>Important Character</text>
	</string>
	<string id="st_ui_pda_companion">
		<text>Companion</text>
	</string>
	<string id="ui_pda_secondary_task">
		<text>Active Tasks</text>
	</string>
	<string id="ui_show_second_task_wnd">
		<text>Hide/Display Task List</text>
	</string>
	<string id="st_ui_pda_actor_box">
		<text>Personal Storage</text>
	</string>
	<string id="st_ui_pda_legend_primary_objects">
		<text>Area</text>
	</string>
	<string id="st_jup_b32_has_af">
		<text>Scanners Detect Artefacts:</text>
	</string>
	<string id="st_jup_b32_no_af">
		<text>Scanners Do Not Detect Artefacts</text>
	</string>
	<string id="st_ui_pda_secret">
		<text>Stash</text>
	</string>
	<string id="st_ui_pda_sleep_place">
		<text>Bed</text>
	</string>
	<string id="st_ui_pda_legend_vip">
		<text>Important Character</text>
	</string>
	<string id="zombie_name">
		<text>John Doe</text>
	</string>
	<string id="arena_enemy">
		<text>Participant</text>
	</string>
	<string id="st_ui_pda_task_unknown_enemy">
		<text>Unknown Enemy</text>
	</string>
	<string id="st_last_seen">
		<text>Last Seen</text>
	</string>
	<string id="pda_table_value_off">
		<text>Display Values</text>
	</string>
	<string id="pda_show_enemy">
		<text>Display Enemies</text>
	</string>
	<string id="st_pda_mode_on">
		<text>On</text>
	</string>
	<string id="st_pda_mode_off">
		<text>Off</text>
	</string>
	<string id="st_pda_mode_dist_far">
		<text>Far</text>
	</string>
	<string id="st_pda_mode_dist_near">
		<text>Near</text>
	</string>
	<string id="st_pda_mode_true">
		<text>True</text>
	</string>
	<string id="st_pda_mode_false">
		<text>False</text>
	</string>
	<string id="st_pda_mode_enabled">
		<text>Enabled</text>
	</string>
	<string id="st_pda_mode_disabled">
		<text>Disabled</text>
	</string>
	<string id="st_pda_distance_state_far">
		<text>Keep Distance Far</text>
	</string>
	<string id="st_pda_distance_state_near">
		<text>Keep Distance Near</text>
	</string>
	<string id="st_pda_cant_trade">
		<text>Task-related stalkers cannot trade</text>
	</string>

<!--
	PDA RELATIONS ACTION LIST
-->

	<string id="st_mm_pda_statistics">
		<text>Statistics</text>
	</string>
	<string id="st_pda_action_1__1">
		<text>Lend Items</text>
	</string>
	<string id="st_pda_action_1__2">
		<text>Commands</text>
	</string>
	<string id="st_pda_action_1__2_2">
		<text>Movement</text>
	</string>
	<string id="st_pda_action_1__2_2_2_on">
		<text>Follow</text>
	</string>
	<string id="st_pda_action_1__2_2_2_off">
		<text>Wait</text>
	</string>
	<string id="st_pda_action_1__2_2_3_on">
		<text>Distance (Near)</text>
	</string>
	<string id="st_pda_action_1__2_2_3_off">
		<text>Distance (Far)</text>
	</string>
	<string id="st_pda_action_1__2_3">
		<text>Combat</text>
	</string>
	<string id="st_pda_action_1__2_4">
		<text>Looting</text>
	</string>
	<string id="st_pda_action_1__2_5_on">
		<text>Stealth (Disable)</text>
	</string>
	<string id="st_pda_action_1__2_5_off">
		<text>Stealth (Enable)</text>
	</string>
	<string id="st_pda_action_1__2_3_2">
		<text>Passive</text>
	</string>
	<string id="st_pda_action_1__2_3_3">
		<text>Defensive</text>
	</string>
	<string id="st_pda_action_1__2_3_4">
		<text>Aggressive</text>
	</string>
	<string id="st_pda_action_1__2_4_2_on">
		<text>Items (Disable)</text>
	</string>
	<string id="st_pda_action_1__2_4_2_off">
		<text>Items (Enable)</text>
	</string>
	<string id="st_pda_action_1__2_4_3_on">
		<text>Corpses (Disable)</text>
	</string>
	<string id="st_pda_action_1__2_4_3_off">
		<text>Corpses (Enable)</text>
	</string>
	<string id="pda_btn_contacts_hint">
		<text>Show Nearby Contacts</text>
	</string>
	<string id="pda_msg_all">
		<text>All</text>
	</string>
	<string id="st_pda_action_back">
		<text>Back</text>
	</string>
	<string id="st_mm_pda_level_travel">
		<text>Level Travel</text>
	</string>
	<string id="st_mm_pda_dismissable">
		<text>Dismissable</text>
	</string>
	<string id="st_mm_pda_stealth">
		<text>Stealth</text>
	</string>
	<string id="st_mm_pda_keep_distance">
		<text>Keep Distance</text>
	</string>
	<string id="st_mm_pda_loot_corpses">
		<text>Loot Corpses</text>
	</string>
	<string id="st_mm_pda_pickup_items">
		<text>Pickup Items</text>
	</string>
	<string id="st_mm_pda_combat">
		<text>Combat</text>
	</string>
	<string id="st_mm_pda_movement">
		<text>Movement</text>
	</string>
	<string id="st_mm_pda_states">
		<text>States</text>
	</string>
	<string id="st_mm_pda_location">
		<text>Location</text>
	</string>
	<string id="st_pda_fast_travel">
		<text>Quick Travel</text>
	</string>
	<string id="st_distance_to">
		<text>Distance To</text>
	</string>
	<string id="st_stash_of">
		<text>Stash Of</text>
	</string>
	
<!--
	WARFARE
-->
	<string id="pda_all_levels">
		<text>All Levels</text>
	</string>
	<string id="pda_current_level">
		<text>Current Level</text>
	</string>
	<string id="ui_st_pda_warfare_squads">
		<text>Total Squads</text>
	</string>
	<string id="ui_st_pda_warfare_capped_smarts">
		<text>Total Outposts</text>
	</string>
	<string id="ui_st_pda_warfare_major_hold">
		<text>Base</text>
	</string>
	<string id="ui_st_pda_warfare_dominance">
		<text>%s are holding %s out of %s outposts in %s</text>
	</string>
	<string id="ui_st_pda_warfare_zone">
		<text>the Zone</text>
	</string>
	
</string_table>